generator/__init__.py
generator/basic_arithmetic.py
generator/main.py
maths_question_generator/__init__.py
maths_question_generator/algebra.py
maths_question_generator/arithmetic.py
maths_question_generator/base.py
maths_question_generator/basic_arithmetic.py
maths_question_generator/utils.py
math_question_generator-2.2.0.dist-info/METADATA
math_question_generator-2.2.0.dist-info/WHEEL
math_question_generator-2.2.0.dist-info/top_level.txt
math_question_generator-2.2.0.dist-info/RECORD
