Metadata-Version: 2.1
Name: math-question-generator
Version: 2.2.0
Summary: Generate math questions & answers
Home-page: https://github.com/shaun-ps-04/math_question_generator
Author: Sean Stocker
Author-email: s.stocker04@outlook.com
License: MIT
Platform: UNKNOWN
Classifier: License :: OSI Approved :: MIT License
Classifier: Programming Language :: Python :: 3
